iapucp_metrix/__init__.py
iapucp_metrix/analyzer.py
iapucp_metrix/models/alonso.csv
iapucp_metrix/models/espal.csv
iapucp_metrix/models/lsa_dictionary.gensim
iapucp_metrix/models/lsa_model.gensim
iapucp_metrix/models/lsa_model.gensim.projection
iapucp_metrix/models/stadthagen.csv
iapucp_metrix/pipes/__init__.py
iapucp_metrix/pipes/additive_connectives_tagger.py
iapucp_metrix/pipes/adversative_connectives_tagger.py
iapucp_metrix/pipes/alphanumeric_word_identifier.py
iapucp_metrix/pipes/causal_connectives_tagger.py
iapucp_metrix/pipes/cohesion_words_tokenizer.py
iapucp_metrix/pipes/content_word_identifier.py
iapucp_metrix/pipes/factory.py
iapucp_metrix/pipes/informative_word_tagger.py
iapucp_metrix/pipes/logical_connectives_tagger.py
iapucp_metrix/pipes/negative_expression_tagger.py
iapucp_metrix/pipes/noun_phrase_tagger.py
iapucp_metrix/pipes/overlap_analyzers.py
iapucp_metrix/pipes/paragraphizer.py
iapucp_metrix/pipes/syllablelizer.py
iapucp_metrix/pipes/temporal_connectives_tagger.py
iapucp_metrix/pipes/verb_phrase_tagger.py
iapucp_metrix/pipes/words_before_main_verb_counter.py
iapucp_metrix/pipes/wrapper_serializer.py
iapucp_metrix/pipes/indices/__init__.py
iapucp_metrix/pipes/indices/connective_indices.py
iapucp_metrix/pipes/indices/descriptive_indices.py
iapucp_metrix/pipes/indices/lexical_diversity_indices.py
iapucp_metrix/pipes/indices/psycholinguistic_indices.py
iapucp_metrix/pipes/indices/readability_indices.py
iapucp_metrix/pipes/indices/referential_cohesion_indices.py
iapucp_metrix/pipes/indices/semantic_cohesion_indices.py
iapucp_metrix/pipes/indices/syntactic_complexity_indices.py
iapucp_metrix/pipes/indices/syntactic_pattern_density_indices.py
iapucp_metrix/pipes/indices/textual_simplicity_indices.py
iapucp_metrix/pipes/indices/word_frequency_indices.py
iapucp_metrix/pipes/indices/word_information_indices.py
iapucp_metrix/utils/__init__.py
iapucp_metrix/utils/conjuntions.py
iapucp_metrix/utils/lsa.py
iapucp_metrix/utils/psycholinguistic.py
iapucp_metrix-0.1.0.dist-info/METADATA
iapucp_metrix-0.1.0.dist-info/WHEEL
iapucp_metrix-0.1.0.dist-info/licenses/LICENSE
iapucp_metrix-0.1.0.dist-info/RECORD
