Metadata-Version: 2.4
Name: iapucp-metrix
Version: 0.1.0
Summary: A comprehensive set of indicators and metrics for assessing text complexity in Spanish.
Author: Alonso Villegas
License-File: LICENSE
Requires-Python: >=3.12
Requires-Dist: datasets>=3.5.0
Requires-Dist: gensim>=4.3.3
Requires-Dist: more-itertools>=10.7.0
Requires-Dist: nltk>=3.9.1
Requires-Dist: pandas>=2.2.3
Requires-Dist: pyphen>=0.17.2
Requires-Dist: rapidfuzz>=3.13.0
Requires-Dist: scipy>=1.13.1
Requires-Dist: spacy>=3.8.4
Requires-Dist: wordfreq>=3.1.1
